tailors/__init__.py
tailors/domains.py
tailors/exceptions.py
tailors/losses.py
tailors/models.py
tailors/plms.py
tailors/metrics/__init__.py
tailors/metrics/cer_metrics.py
tailors/metrics/classification_metrics.py
tailors/metrics/quad_metrics.py
tailors/metrics/sequence_metrics.py
tailors/trainer/README.md
tailors/trainer/__init__.py
tailors/trainer/callbacks.py
tailors/trainer/cartographer.py
tailors/trainer/data.py
tailors/trainer/dataset_from_eb.py
tailors/trainer/domains.py
tailors/trainer/exceptions.py
tailors/trainer/optimizers.py
tailors/trainer/pefts.py
tailors/trainer/schedulers.py
tailors/trainer/train.py
tailors/trainer/trainer.py
tailors/trainer/ui/__init__.py
tailors/trainer/ui/app.py
tailors/trainer/ui/auths.py
tailors/trainer/ui/domains.py
tailors/trainer/ui/exceptions.py
tailors/trainer/ui/runner.py
tailors/trainer/ui/scheduled.py
tailors/trainer/ui/unsecure.py
tailors/trainer/ui/utils.py
tailors/trainer/ui/statics/favicon.ico
tailors/trainer/ui/statics/index.html
tailors/trainer/ui/statics/assets/404-1ad791c2.js
tailors/trainer/ui/statics/assets/ext-searchbox-40b2113a.js
tailors/trainer/ui/statics/assets/html-bfd118fb.js
tailors/trainer/ui/statics/assets/iconify-0f6e8de0.js
tailors/trainer/ui/statics/assets/index-e2caacdf.css
tailors/trainer/ui/statics/assets/index-e9cad759.js
tailors/trainer/ui/statics/assets/javascript-adb9f602.js
tailors/trainer/ui/statics/assets/login-018d451e.js
tailors/trainer/ui/statics/assets/logs-a48439dc.js
tailors/trainer/ui/statics/assets/mode-html-f3d797fd.js
tailors/trainer/ui/statics/assets/mode-javascript-8abd7a17.js
tailors/trainer/ui/statics/assets/mode-json-812ca1e1.js
tailors/trainer/ui/statics/assets/mode-yaml-202fbe23.js
tailors/trainer/ui/statics/assets/task-a3109ad4.js
tailors/trainer/ui/statics/assets/tasks-6184e015.js
tailors/trainer/ui/statics/assets/theme-dracula-2432079e.js
tailors/trainer/ui/statics/assets/worker-base-78504947.js
tailors/trainer/ui/statics/assets/worker-html-a0682eba.js
tailors-0.1.5.dist-info/entry_points.txt
tailors-0.1.5.dist-info/LICENSE
tailors-0.1.5.dist-info/WHEEL
tailors-0.1.5.dist-info/METADATA
tailors-0.1.5.dist-info/RECORD
